rackspaceauth-0.8.1.dist-info/RECORD
rackspaceauth-0.8.1.dist-info/metadata.json
rackspaceauth-0.8.1.dist-info/WHEEL
rackspaceauth-0.8.1.dist-info/entry_points.txt
rackspaceauth-0.8.1.dist-info/DESCRIPTION.rst
rackspaceauth-0.8.1.dist-info/pbr.json
rackspaceauth-0.8.1.dist-info/top_level.txt
rackspaceauth-0.8.1.dist-info/METADATA
rackspaceauth/__init__.py
rackspaceauth/v2.py
rackspaceauth/.travis.yml
rackspaceauth/loading/__init__.py
rackspaceauth/loading/v2.py
rackspaceauth/tests/__init__.py
rackspaceauth/tests/unit/__init__.py
rackspaceauth/tests/unit/test_rackspaceauth.py
