Metadata-Version: 2.0
Name: rackspaceauth
Version: 0.8.1
Summary: keystoneauth plugin for Rackspace's authentication service
Home-page: https://developer.rackspace.com/
Author: Brian Curtin
Author-email: brian.curtin@rackspace.com
License: UNKNOWN
Platform: UNKNOWN
Classifier: Environment :: OpenStack
Classifier: Intended Audience :: Information Technology
Classifier: Intended Audience :: System Administrators
Classifier: License :: OSI Approved :: Apache Software License
Classifier: Operating System :: POSIX :: Linux
Classifier: Development Status :: 4 - Beta
Classifier: Programming Language :: Python
Classifier: Programming Language :: Python :: 2
Classifier: Programming Language :: Python :: 2.7
Classifier: Programming Language :: Python :: 3
Classifier: Programming Language :: Python :: 3.4
Requires-Dist: pbr (>=1.6)
Requires-Dist: keystoneauth1 (>=3.3.0)
Requires-Dist: requests (>=2.16.0)
Requires-Dist: urllib3
